<?xml version="1.0" encoding="UTF-8"?>
<objects serializationModel="Studio.02.02.00">
	<object class="AudioFile" id="{cc95138c-15d8-4537-b444-e4a3fbf26c99}">
		<property name="assetPath">
			<value>BUBBLE_TUTORIAL_MESSAGE.ogg</value>
		</property>
		<property name="frequencyInKHz">
			<value>48</value>
		</property>
		<property name="channelCount">
			<value>1</value>
		</property>
		<property name="length">
			<value>0.33333333333333331</value>
		</property>
		<relationship name="masterAssetFolder">
			<destination>{98f70223-beac-4cb9-9adf-cf1139468f37}</destination>
		</relationship>
	</object>
</objects>
